physique/__init__.py
physique/csv.py
physique/fonctions.py
physique/modelisation.py
physique/signal.py
physique-0.6.0.dist-info/LICENSE
physique-0.6.0.dist-info/METADATA
physique-0.6.0.dist-info/WHEEL
physique-0.6.0.dist-info/top_level.txt
physique-0.6.0.dist-info/RECORD
