Metadata-Version: 2.1
Name: physique
Version: 0.6.0
Summary: Librairie Python pour les sciences physiques
Home-page: https://github.com/david-therincourt/physique
Author: David THERINCOURT
Author-email: dtherincourt@gmail.com
Classifier: Programming Language :: Python :: 3
Classifier: License :: OSI Approved :: MIT License
Classifier: Operating System :: OS Independent
Requires-Python: >=3.6
License-File: LICENSE
